{
  "project_info": {
    "project_number": "279927253519",
    "project_id": "trialog-8a95b",
    "storage_bucket": "trialog-8a95b.firebasestorage.app"
  },
  "client": [
    {
      "client_info": {
        "mobilesdk_app_id": "1:279927253519:android:bf9a23e6ebe5715641d17a",
        "android_client_info": {
          "package_name": "com.example.trialog"
        }
      },
      "oauth_client": [],
      "api_key": [
        {
          "current_key": "AIzaSyA-m6SgJOMsySdYWCbwv_NUNPL8kbaZmSE"
        }
      ],
      "services": {
        "appinvite_service": {
          "other_platform_oauth_client": []
        }
      }
    }
  ],
  "configuration_version": "1"
}